Metadata-Version: 2.1
Name: ubit-autolab-auto-submit
Version: 0.0.3
Summary: Automated AutoLab Submissions
Requires-Python: >=3.6, <4
